caesar_cipher/__init__.py
caesar_cipher/alphabets.py
caesar_cipher/caesar_cipher.py
caesar_cipher/decryption.py
caesar_cipher/encryption.py
caesar_cipher/get_input.py
caesar_cipher/messages.py
caesar_cipher/offline_quotes.py
caesar_cipher/quotes.py
jc_cipher-0.0.9.dist-info/LICENSE
jc_cipher-0.0.9.dist-info/METADATA
jc_cipher-0.0.9.dist-info/WHEEL
jc_cipher-0.0.9.dist-info/entry_points.txt
jc_cipher-0.0.9.dist-info/top_level.txt
jc_cipher-0.0.9.dist-info/RECORD
